BoreholeGeomechanics
