Metadata-Version: 2.1
Name: BoreholeGeomechanics
Version: 1.0.3
Summary: BoreholeGeomechanics
Home-page: UNKNOWN
Author: Mai Linh Doan & Lahcene Bellounis
License: GPL-3.0
Platform: UNKNOWN
Classifier: License :: OSI Approved :: GNU General Public License v3 (GPLv3)
Classifier: Programming Language :: Python :: 3
Classifier: Programming Language :: Python :: 3.8
License-File: LICENSE
